flask_jwt/__init__.py
webstack_flask_jwt-0.4.dist-info/DESCRIPTION.rst
webstack_flask_jwt-0.4.dist-info/METADATA
webstack_flask_jwt-0.4.dist-info/RECORD
webstack_flask_jwt-0.4.dist-info/WHEEL
webstack_flask_jwt-0.4.dist-info/metadata.json
webstack_flask_jwt-0.4.dist-info/top_level.txt
