Metadata-Version: 2.0
Name: webstack-flask-jwt
Version: 0.4
Summary: JWT token authentication for Flask apps
Home-page: https://github.com/webstack/flask-jwt
Author: Matt Wright
Author-email: matt@nobien.net
License: MIT
Platform: any
Classifier: Development Status :: 5 - Production/Stable
Classifier: Environment :: Web Environment
Classifier: Intended Audience :: Developers
Classifier: License :: OSI Approved :: MIT License
Classifier: Operating System :: OS Independent
Classifier: Programming Language :: Python
Classifier: Topic :: Internet :: WWW/HTTP :: Dynamic Content
Classifier: Topic :: Software Development :: Libraries :: Python Modules
Requires-Dist: Flask (>=0.9)
Requires-Dist: PyJWT (>=1.4.0,<1.5.0)
